gcal2redmine/__init__.py
gcal2redmine/cli.py
gcal2redmine/gcal.py
gcal2redmine/redmine.py
gcal2redmine/utils.py
gcal2redmine-0.3.0.post2.dist-info/LICENSE
gcal2redmine-0.3.0.post2.dist-info/METADATA
gcal2redmine-0.3.0.post2.dist-info/WHEEL
gcal2redmine-0.3.0.post2.dist-info/entry_points.txt
gcal2redmine-0.3.0.post2.dist-info/top_level.txt
gcal2redmine-0.3.0.post2.dist-info/RECORD
