Metadata-Version: 2.1
Name: gcal2redmine
Version: 0.3.0.post2
Summary: Fill Redmine time tracker from a Google Calendar
Home-page: https://git.ubicast.net/nkarolak/gcal2redmine
Author: Nicolas KAROLAK
Author-email: nicolas.karolak@ubicast.eu
License: WTFPL
Download-URL: https://git.ubicast.net/nkarolak/gcal2redmine/-/archive/master/gcal2redmine-master.tar.gz
Keywords: redmine,google calendar,time tracking
Platform: UNKNOWN
Classifier: Development Status :: 4 - Beta
Classifier: Environment :: Console
Classifier: Operating System :: POSIX :: Linux
Classifier: Topic :: Office/Business :: Scheduling
Classifier: Topic :: Software Development :: Bug Tracking
Requires-Dist: google-api-python-client (~=1.7)
Requires-Dist: python-redmine (~=2.1)
Requires-Dist: oauth2client (~=4.1)
Requires-Dist: click (~=7.0)
Requires-Dist: tzlocal (~=1.5)
Provides-Extra: dev
Requires-Dist: black ; extra == 'dev'
Requires-Dist: flake8 ; extra == 'dev'
Requires-Dist: mypy ; extra == 'dev'
Requires-Dist: pylint ; extra == 'dev'
Requires-Dist: twine ; extra == 'dev'
